forkyeah/__init__.py
forkyeah/cli.py
forkyeah/git.py
forkyeah-0.0.2.dist-info/METADATA
forkyeah-0.0.2.dist-info/RECORD
forkyeah-0.0.2.dist-info/WHEEL
forkyeah-0.0.2.dist-info/entry_points.txt
forkyeah-0.0.2.dist-info/top_level.txt
