Metadata-Version: 2.1
Name: forkyeah
Version: 0.0.2
Summary: forkyeah is a small tool for managing patches on an upstream git repo.
Home-page: UNKNOWN
Author: Mike Purvis
Author-email: mpurvis@clearpath.ai
License: Apache 2.0
Platform: UNKNOWN
Requires-Dist: requests
Requires-Dist: setuptools
Requires-Dist: empy
Requires-Dist: PyYAML
